alist_v3/__init__.py
alist_v3/admin.py
alist_v3/auth.py
alist_v3/fs.py
alist_v3/lib.py
alist_v3/public.py
alist_v3-0.1.1.dist-info/LICENSE
alist_v3-0.1.1.dist-info/METADATA
alist_v3-0.1.1.dist-info/WHEEL
alist_v3-0.1.1.dist-info/top_level.txt
alist_v3-0.1.1.dist-info/RECORD
