Metadata-Version: 2.1
Name: alist-v3
Version: 0.1.1
Summary: Write for alist V3
Home-page: https://github.com/IamK77/alist_v3
Author: Iamk77
Author-email: chenyinfeng50@qq.com
Classifier: Programming Language :: Python :: 3
Classifier: License :: OSI Approved :: Apache Software License
Classifier: Operating System :: OS Independent
License-File: LICENSE
Requires-Dist: aiohttp
